.git-blame-ignore-revs
.pre-commit-config.yaml
LICENSE
README.md
pyproject.toml
setup.py
.github/workflows/cd.yml
.github/workflows/ci.yml
.github/workflows/latest-python.yml
pipic/__init__.py
pipic/__init__.pyi
pipic/_version.py
pipic/consts.py
pipic/ctypes.py
pipic/tools.py
pipic.egg-info/PKG-INFO
pipic.egg-info/SOURCES.txt
pipic.egg-info/dependency_links.txt
pipic.egg-info/requires.txt
pipic.egg-info/top_level.txt
pipic/extensions/__init__.py
pipic/extensions/x_reflector_py.py
pipic/interfaces/__init__.py
pipic/interfaces/cellinterface.py
pipic/types/__init__.py
pipic/types/callbacks.py
pipic/types/double3.py
pipic/types/int3.py
src/CMakeLists.txt
src/ec2_solver.h
src/ec_solver.h
src/ensemble.h
src/fourier_boris_solver.h
src/fourier_solver.h
src/interfaces.h
src/pipic.cpp
src/pipic.h
src/primitives.h
src/services.h
src/extensions/downsampler_gonoskov2022/downsampler_gonoskov2022.cpp
src/extensions/focused_pulse/focused_pulse.cpp
src/extensions/landau_lifshitz/landau_lifshitz.cpp
src/extensions/qed_gonoskov2015/qed_gonoskov2015.cpp
src/extensions/qed_gonoskov2015/synchrotron_functions.py
src/extensions/qed_volokitin2023/QED_emis.in
src/extensions/qed_volokitin2023/QED_pair_half.in
src/extensions/qed_volokitin2023/breit_wheeler.h
src/extensions/qed_volokitin2023/compton.h
src/extensions/qed_volokitin2023/qed_volokitin2023.cpp
src/extensions/x_converter_c/x_converter_c.cpp
src/extensions/x_reflector_c/x_reflector_c.cpp