Metadata-Version: 2.1
Name: pipic
Version: 1.2
Summary: A Python library for particle-in-cell plasma simulation.
Author-email: Arkady Gonoskov <arkady.gonoskov@physics.gu.se>
Maintainer: The pipic developers team
Project-URL: Homepage, https://github.com/hi-chi/pipic
Project-URL: Issues, https://github.com/hi-chi/pipic/issues
Classifier: Development Status :: 5 - Production/Stable
Classifier: License :: OSI Approved :: GNU General Public License v3 (GPLv3)
Classifier: Operating System :: OS Independent
Classifier: Programming Language :: Python :: 3 :: Only
Classifier: Programming Language :: Python :: 3
Classifier: Programming Language :: Python :: 3.8
Classifier: Programming Language :: Python :: 3.9
Classifier: Programming Language :: Python :: 3.10
Classifier: Programming Language :: Python :: 3.11
Classifier: Programming Language :: Python :: 3.12
Classifier: Intended Audience :: Science/Research
Classifier: Topic :: Scientific/Engineering :: Physics
Requires-Python: >=3.8
License-File: LICENSE
Requires-Dist: numpy>=1.19; python_version ~= "3.8"
Requires-Dist: numpy>=1.20; python_version ~= "3.9"
Requires-Dist: numpy>=1.22; python_version ~= "3.10"
Requires-Dist: numpy>=1.24; python_version >= "3.11"
Requires-Dist: numpy>=1.26; python_version >= "3.12"
Requires-Dist: numba>=0.49; python_version ~= "3.8"
Requires-Dist: numba>=0.53; python_version ~= "3.9"
Requires-Dist: numba>=0.55; python_version ~= "3.10"
Requires-Dist: numba>=0.57; python_version >= "3.11"
Requires-Dist: numba>=0.59; python_version >= "3.12"
Provides-Extra: mpl
Requires-Dist: matplotlib; extra == "mpl"
Provides-Extra: test
Requires-Dist: pytest; extra == "test"
Provides-Extra: docs
Requires-Dist: sphinx; extra == "docs"
Requires-Dist: sphinx_rtd_theme; extra == "docs"
Provides-Extra: dev
Requires-Dist: pipic[mpl,test]; extra == "dev"
Requires-Dist: setuptools>=64; extra == "dev"
Requires-Dist: setuptools-scm>=8; extra == "dev"
Requires-Dist: wheel; extra == "dev"
Requires-Dist: pybind11; extra == "dev"
